mcp_server_law_recognition/__init__.py
mcp_server_law_recognition/__main__.py
mcp_server_law_recognition/server.py
mcp_server_law_recognition-0.1.1.dist-info/licenses/LICENSE
mcp_server_law_recognition-0.1.1.dist-info/METADATA
mcp_server_law_recognition-0.1.1.dist-info/WHEEL
mcp_server_law_recognition-0.1.1.dist-info/entry_points.txt
mcp_server_law_recognition-0.1.1.dist-info/top_level.txt
mcp_server_law_recognition-0.1.1.dist-info/RECORD
