Metadata-Version: 2.4
Name: mcp_server_law_recognition
Version: 0.1.1
Summary: MCP server for retrieving issues from law_recognition
License: Copyright (c) 2021 The Python Packaging Authority
Classifier: Programming Language :: Python :: 3
Classifier: License :: OSI Approved :: MIT License
Classifier: Operating System :: OS Independent
Requires-Python: >=3.10
License-File: LICENSE
Requires-Dist: mcp>=1.0.0
Dynamic: license-file
